boolsim.py
boolsim_setup.py
boolsim-0.5.dist-info/METADATA
boolsim-0.5.dist-info/WHEEL
boolsim-0.5.dist-info/top_level.txt
boolsim-0.5.dist-info/RECORD
