Metadata-Version: 2.1
Name: boolsim
Version: 0.5
Summary: Python interface to boolSim
Home-page: https://github.com/colomoto/boolSim-python
Author: Loïc Paulevé
Author-email: loic.pauleve@labri.fr
License: UNKNOWN
Keywords: computational systems biology
Platform: UNKNOWN
Classifier: Intended Audience :: Science/Research
Classifier: Topic :: Scientific/Engineering :: Bio-Informatics
Requires-Dist: colomoto-jupyter (>=0.7.0)
Requires-Dist: pandas
